xmindparserpro/__init__.py
xmindparserpro/main.py
xmindparserpro/xreader.py
xmindparserpro/zenreader.py
xmindparserpro-0.0.1.dist-info/METADATA
xmindparserpro-0.0.1.dist-info/WHEEL
xmindparserpro-0.0.1.dist-info/entry_points.txt
xmindparserpro-0.0.1.dist-info/top_level.txt
xmindparserpro-0.0.1.dist-info/RECORD
