Metadata-Version: 2.1
Name: xmindparserpro
Version: 0.0.1
Summary: xmindparser优化版
Home-page: https://github.com/maiyajj/xmindparserpro
Author: maiyajj
Author-email: 
Classifier: License :: OSI Approved :: MIT License
Classifier: Programming Language :: Python :: 3.6
Classifier: Programming Language :: Python :: 3.7
Classifier: Programming Language :: Python :: 3.8
Classifier: Programming Language :: Python :: 3.9
Classifier: Programming Language :: Python :: 3.10
Classifier: Programming Language :: Python :: 3.11
Classifier: Programming Language :: Python :: 3.12
Classifier: Programming Language :: Python :: 3.13
Requires-Python: >=3.6.0
